rb_resume_parser-0.1.6.dist-info/licenses/LICENSE
resume_parser/__init__.py
resume_parser/resume_parser.py
rb_resume_parser-0.1.6.dist-info/METADATA
rb_resume_parser-0.1.6.dist-info/WHEEL
rb_resume_parser-0.1.6.dist-info/top_level.txt
rb_resume_parser-0.1.6.dist-info/RECORD
