Metadata-Version: 2.4
Name: rb-resume-parser
Version: 0.1.6
Summary: Extract structured information from PDF resumes using NLP and pattern matching
Author-email: Rahul Bagai <rahulbagai@ieee.org>
License: MIT
Project-URL: Homepage, https://github.com/rahulbagai/resume-parser
Project-URL: Documentation, https://github.com/rahulbagai/resume-parser#readme
Project-URL: Issues, https://github.com/rahulbagai/resume-parser/issues
Project-URL: Source, https://github.com/rahulbagai/resume-parser
Keywords: resume,parser,pdf,nlp,cv,extraction
Classifier: License :: OSI Approved :: MIT License
Classifier: Programming Language :: Python :: 3
Classifier: Development Status :: 4 - Beta
Classifier: Intended Audience :: Developers
Classifier: Topic :: Text Processing :: Linguistic
Requires-Python: >=3.9
License-File: LICENSE
Requires-Dist: pymupdf>=1.23.0
Requires-Dist: spacy<4.0.0,>=3.0.0
Provides-Extra: dev
Requires-Dist: pytest>=7.0.0; extra == "dev"
Requires-Dist: pytest-cov>=4.0.0; extra == "dev"
Requires-Dist: black>=23.0.0; extra == "dev"
Requires-Dist: mypy>=1.0.0; extra == "dev"
Requires-Dist: ruff>=0.1.0; extra == "dev"
Requires-Dist: bump2version>=1.0.0; extra == "dev"
Dynamic: license-file
